[
    {
        "key": "dbln",
        "value": "%7B%2261575219581483%22%3A%22yWvwyCV2%22%7D",
        "domain": "facebook.com",
        "path": "/login/device-based/",
        "hostOnly": false,
        "creation": "2025-06-28T10:32:49.040Z",
        "lastAccessed": "2025-06-28T10:32:49.045Z"
    },
    {
        "key": "datr",
        "value": "51BQaP21b5ZrfWPOUPOGAU00",
        "domain": "facebook.com",
        "path": "/",
        "hostOnly": false,
        "creation": "2025-06-28T10:32:49.045Z",
        "lastAccessed": "2025-06-28T10:32:49.045Z"
    },
    {
        "key": "sb",
        "value": "51BQaIh3Rf9kELBjT31euMPD",
        "domain": "facebook.com",
        "path": "/",
        "hostOnly": false,
        "creation": "2025-06-28T10:32:49.045Z",
        "lastAccessed": "2025-06-28T10:32:49.045Z"
    },
    {
        "key": "ps_l",
        "value": "1",
        "domain": "facebook.com",
        "path": "/",
        "hostOnly": false,
        "creation": "2025-06-28T10:32:49.045Z",
        "lastAccessed": "2025-06-28T10:32:49.045Z"
    },
    {
        "key": "ps_n",
        "value": "1",
        "domain": "facebook.com",
        "path": "/",
        "hostOnly": false,
        "creation": "2025-06-28T10:32:49.045Z",
        "lastAccessed": "2025-06-28T10:32:49.045Z"
    },
    {
        "key": "vpd",
        "value": "v1%3B724x384x1.875",
        "domain": "facebook.com",
        "path": "/",
        "hostOnly": false,
        "creation": "2025-06-28T10:32:49.045Z",
        "lastAccessed": "2025-06-28T10:32:49.045Z"
    },
    {
        "key": "locale",
        "value": "en_US",
        "domain": "facebook.com",
        "path": "/",
        "hostOnly": false,
        "creation": "2025-06-28T10:32:49.045Z",
        "lastAccessed": "2025-06-28T10:32:49.045Z"
    },
    {
        "key": "m_pixel_ratio",
        "value": "1.875",
        "domain": "facebook.com",
        "path": "/",
        "hostOnly": false,
        "creation": "2025-06-28T10:32:49.045Z",
        "lastAccessed": "2025-06-28T10:32:49.045Z"
    },
    {
        "key": "wd",
        "value": "385x854",
        "domain": "facebook.com",
        "path": "/",
        "hostOnly": false,
        "creation": "2025-06-28T10:32:49.045Z",
        "lastAccessed": "2025-06-28T10:32:49.045Z"
    },
    {
        "key": "c_user",
        "value": "61575219581483",
        "domain": "facebook.com",
        "path": "/",
        "hostOnly": false,
        "creation": "2025-06-28T10:32:49.045Z",
        "lastAccessed": "2025-06-28T10:32:49.045Z"
    },
    {
        "key": "xs",
        "value": "36%3AeaG7s23VoPiWcw%3A2%3A1751106622%3A-1%3A-1",
        "domain": "facebook.com",
        "path": "/",
        "hostOnly": false,
        "creation": "2025-06-28T10:32:49.045Z",
        "lastAccessed": "2025-06-28T10:32:49.045Z"
    },
    {
        "key": "fr",
        "value": "0K1dwfP83rtmlQwWg.AWcKleRl0ei8EQDX3t3oNrF1TG0L9tw5vI6sGfYXmH0TCDNmT_w.BoUFDn..AAA.0.0.BoX8RC.AWeIefclNrCiBm4hwj1Tj55Jlxs",
        "domain": "facebook.com",
        "path": "/",
        "hostOnly": false,
        "creation": "2025-06-28T10:32:49.045Z",
        "lastAccessed": "2025-06-28T10:32:49.045Z"
    },
    {
        "key": "fbl_st",
        "value": "100435310%3BT%3A29185110",
        "domain": "facebook.com",
        "path": "/",
        "hostOnly": false,
        "creation": "2025-06-28T10:32:49.045Z",
        "lastAccessed": "2025-06-28T10:32:49.045Z"
    },
    {
        "key": "wl_cbv",
        "value": "v2%3Bclient_version%3A2856%3Btimestamp%3A1751106626",
        "domain": "facebook.com",
        "path": "/",
        "hostOnly": false,
        "creation": "2025-06-28T10:32:49.045Z",
        "lastAccessed": "2025-06-28T10:32:49.045Z"
    }
        ]
